dsci524_group29_webscraping/__init__.py
dsci524_group29_webscraping/fetch_html.py
dsci524_group29_webscraping/parse_content.py
dsci524_group29_webscraping/save_data.py
dsci524_group29_webscraping-1.1.8.dist-info/LICENSE
dsci524_group29_webscraping-1.1.8.dist-info/METADATA
dsci524_group29_webscraping-1.1.8.dist-info/WHEEL
dsci524_group29_webscraping-1.1.8.dist-info/RECORD
