Metadata-Version: 2.3
Name: dsci524_group29_webscraping
Version: 1.1.8
Summary: A simple Python toolkit for web scraping
License: MIT
Author: Lixuan Lin
Requires-Python: >=3.9,<4.0
Classifier: License :: OSI Approved :: MIT License
Classifier: Programming Language :: Python :: 3
Classifier: Programming Language :: Python :: 3.9
Classifier: Programming Language :: Python :: 3.10
Classifier: Programming Language :: Python :: 3.11
Classifier: Programming Language :: Python :: 3.12
Classifier: Programming Language :: Python :: 3.13
Requires-Dist: cssselect (>=1.2.0,<2.0.0)
Requires-Dist: lxml (>=5.3.0,<6.0.0)
Requires-Dist: requests (>=2.32.3,<3.0.0)
